{
  "metadata": {
    "source": "U.S. Census Bureau American Community Survey",
    "dataset": "ACS 5-Year Estimates 2023",
    "state": "Idaho",
    "state_fips": "16",
    "geography": "State",
    "fetched_at": "2026-01-16T04:50:35.269021"
  },
  "data": {
    "total_population": 1893296,
    "median_age": 37,
    "male_under_5": 57953,
    "male_5_to_9": 65629,
    "male_10_to_14": 70855,
    "male_15_to_17": 43375,
    "male_18_to_19": 27822,
    "male_20": 13809,
    "male_21": 14065,
    "male_22_to_24": 37532,
    "male_25_to_29": 62964,
    "male_30_to_34": 62299,
    "male_35_to_39": 62944,
    "male_40_to_44": 62297,
    "male_45_to_49": 55712,
    "male_50_to_54": 53711,
    "male_55_to_59": 54200,
    "male_60_to_61": 23288,
    "male_62_to_64": 33891,
    "male_65_to_66": 21949,
    "male_67_to_69": 28906,
    "male_70_to_74": 43502,
    "male_75_to_79": 26831,
    "male_80_to_84": 16749,
    "male_85_plus": 11797,
    "female_under_5": 55313,
    "female_5_to_9": 62321,
    "female_10_to_14": 67122,
    "female_15_to_17": 40599,
    "female_18_to_19": 32908,
    "female_20": 12978,
    "female_21": 12233,
    "female_22_to_24": 34463,
    "female_25_to_29": 58882,
    "female_30_to_34": 61010,
    "female_35_to_39": 60460,
    "female_40_to_44": 60545,
    "female_45_to_49": 52535,
    "female_50_to_54": 51841,
    "female_55_to_59": 54495,
    "female_60_to_61": 23252,
    "female_62_to_64": 35602,
    "female_65_to_66": 23909,
    "female_67_to_69": 29936,
    "female_70_to_74": 44750,
    "female_75_to_79": 29865,
    "female_80_to_84": 18118,
    "female_85_plus": 18079,
    "median_household_income": 74636,
    "per_capita_income": 37169,
    "poverty_universe": 1843325,
    "poverty_total": 196060,
    "employment_universe_16plus": 1484640,
    "in_labor_force": 935761,
    "civilian_labor_force": 930589,
    "employed": 896360,
    "unemployed": 34229,
    "not_in_labor_force": 548879,
    "industry_total": 896360,
    "industry_agriculture": 29690,
    "industry_construction": 73923,
    "industry_manufacturing": 61410,
    "industry_wholesale": 16252,
    "industry_retail": 54506,
    "industry_transportation": 34299,
    "industry_finance": 8284,
    "industry_professional": 52241,
    "industry_education_healthcare": 53214,
    "industry_arts_entertainment": 36434,
    "industry_other_services": 19894,
    "industry_public_admin": 23983,
    "education_universe_25plus": 1244319,
    "edu_no_schooling": 15009,
    "edu_high_school": 262971,
    "edu_ged": 59602,
    "edu_some_college_less_1yr": 99796,
    "edu_some_college_1yr_plus": 208911,
    "edu_associates": 121437,
    "edu_bachelors": 258838,
    "edu_masters": 91217,
    "edu_professional": 21392,
    "edu_doctorate": 16585,
    "housing_units_total": 776683,
    "housing_occupied": 693821,
    "housing_vacant": 82862,
    "tenure_total": 693821,
    "owner_occupied": 502140,
    "renter_occupied": 191681,
    "median_home_value": 376000,
    "median_gross_rent": 1150,
    "structure_1_detached": 574147,
    "structure_mobile_home": 56490,
    "health_insurance_universe": 1866785,
    "insured_male_under_6": 66458,
    "insured_male_6_to_18": 169287,
    "insured_male_19_to_25": 72640,
    "insured_male_26_to_34": 88376,
    "insured_male_35_to_44": 104676,
    "insured_male_45_to_54": 93370,
    "insured_male_55_to_64": 97670,
    "insured_male_65_to_74": 92590,
    "insured_male_75_plus": 53238,
    "insured_female_under_6": 64449,
    "insured_female_6_to_18": 164905,
    "insured_female_19_to_25": 74848,
    "insured_female_26_to_34": 92435,
    "insured_female_35_to_44": 105493,
    "insured_female_45_to_54": 92059,
    "insured_female_55_to_64": 101951,
    "insured_female_65_to_74": 96859,
    "insured_female_75_plus": 62134,
    "disability_universe": 1866785,
    "disability_male_under_5": 386,
    "disability_male_5_to_17": 12505,
    "disability_male_18_to_34": 18869,
    "disability_male_35_to_64": 48199,
    "disability_male_65_to_74": 26273,
    "disability_male_75_plus": 26933,
    "disability_female_under_5": 306,
    "disability_female_5_to_17": 8692,
    "disability_female_18_to_34": 18809,
    "disability_female_35_to_64": 44543,
    "disability_female_65_to_74": 22364,
    "disability_female_75_plus": 29325,
    "households_total": 693821,
    "family_households": 476181,
    "married_couple_family": 382744,
    "male_householder_no_spouse": 33260,
    "female_householder_no_spouse": 60177,
    "nonfamily_households": 217640,
    "children_in_households": 462053,
    "veterans_universe_18plus": 1424957,
    "veterans_total": 117609,
    "commute_total": 885092,
    "commute_car_alone": 650915,
    "commute_carpool": 79547,
    "commute_public_transit": 5175,
    "commute_walk": 24169,
    "commute_work_from_home": 108150,
    "vehicles_households_total": 693821,
    "vehicles_0": 25859,
    "internet_universe": 693821,
    "internet_any": 633140,
    "internet_broadband": 631601,
    "internet_none": 41271,
    "computer_universe": 693821,
    "computer_has": 665435,
    "language_universe_5plus": 1780030,
    "language_english_only": 1589255,
    "language_spanish": 142101,
    "citizenship_universe": 1893296,
    "citizen_born_us": 1765328,
    "citizen_naturalized": 49860,
    "not_citizen": 58726,
    "derived": {
      "age_under_5": 113266,
      "age_5_to_17": 349901,
      "age_65_plus": 314391,
      "poverty_rate_pct": 10.6,
      "homeownership_rate_pct": 72.4,
      "unemployment_rate_pct": 3.7,
      "labor_force_participation_pct": 63.0,
      "broadband_access_pct": 91.0,
      "no_internet_pct": 5.9,
      "veteran_rate_pct": 8.3,
      "work_from_home_pct": 12.2,
      "college_degree_pct": 31.2,
      "industry_agriculture_pct": 3.3,
      "industry_construction_pct": 8.2,
      "industry_manufacturing_pct": 6.9,
      "industry_retail_pct": 6.1,
      "industry_education_healthcare_pct": 5.9,
      "industry_public_admin_pct": 2.7
    }
  }
}